setup.py
matrella_distributions/Binomialdistribution.py
matrella_distributions/Gaussiandistribution.py
matrella_distributions/Generaldistribution.py
matrella_distributions/__init__.py
matrella_distributions.egg-info/PKG-INFO
matrella_distributions.egg-info/SOURCES.txt
matrella_distributions.egg-info/dependency_links.txt
matrella_distributions.egg-info/not-zip-safe
matrella_distributions.egg-info/top_level.txt