Metadata-Version: 1.0
Name: matrella-distributions
Version: 0.1
Summary: Gaussian & Binomial distributions
Home-page: UNKNOWN
Author: Mathieu Rella
Author-email: UNKNOWN
License: UNKNOWN
Platform: UNKNOWN
